palindromicprimes/PalindromicPrimes.py
palindromicprimes/__init__.py
palindromicprimes-1.0.1.dist-info/LICENSE.md
palindromicprimes-1.0.1.dist-info/METADATA
palindromicprimes-1.0.1.dist-info/WHEEL
palindromicprimes-1.0.1.dist-info/top_level.txt
palindromicprimes-1.0.1.dist-info/RECORD
